.editorconfig
.gitignore
.nojekyll
.travis.yml
AUTHORS.rst
CONTRIBUTING.rst
HISTORY.rst
LICENSE
MANIFEST.in
Makefile
README.rst
index.html
notes.txt
publish.sh
requirements_dev.txt
setup.cfg
setup.py
tox.ini
.github/ISSUE_TEMPLATE.md
docs/Makefile
docs/authors.rst
docs/conf.py
docs/contributing.rst
docs/history.rst
docs/index.rst
docs/installation.rst
docs/make.bat
docs/readme.rst
docs/usage.rst
docs/_build/singlehtml/index.html
docs/_build/singlehtml/_static/ajax-loader.gif
docs/_build/singlehtml/_static/alabaster.css
docs/_build/singlehtml/_static/basic.css
docs/_build/singlehtml/_static/comment-bright.png
docs/_build/singlehtml/_static/comment-close.png
docs/_build/singlehtml/_static/comment.png
docs/_build/singlehtml/_static/custom.css
docs/_build/singlehtml/_static/doctools.js
docs/_build/singlehtml/_static/documentation_options.js
docs/_build/singlehtml/_static/down-pressed.png
docs/_build/singlehtml/_static/down.png
docs/_build/singlehtml/_static/file.png
docs/_build/singlehtml/_static/jquery-3.2.1.js
docs/_build/singlehtml/_static/jquery.js
docs/_build/singlehtml/_static/language_data.js
docs/_build/singlehtml/_static/minus.png
docs/_build/singlehtml/_static/plus.png
docs/_build/singlehtml/_static/pygments.css
docs/_build/singlehtml/_static/searchtools.js
docs/_build/singlehtml/_static/underscore-1.3.1.js
docs/_build/singlehtml/_static/underscore.js
docs/_build/singlehtml/_static/up-pressed.png
docs/_build/singlehtml/_static/up.png
docs/_build/singlehtml/_static/websupport.js
kinet2pcb/__init__.py
kinet2pcb/kinet2pcb.py
kinet2pcb/pckg_info.py
kinet2pcb.egg-info/PKG-INFO
kinet2pcb.egg-info/SOURCES.txt
kinet2pcb.egg-info/dependency_links.txt
kinet2pcb.egg-info/entry_points.txt
kinet2pcb.egg-info/not-zip-safe
kinet2pcb.egg-info/requires.txt
kinet2pcb.egg-info/top_level.txt
tests/conftest.py
tests/test_1.brd
tests/test_1.kicad_prl
tests/test_1.kicad_pro
tests/test_kinet2pcb.py
tests/kinet2pcb_test/fp-info-cache
tests/kinet2pcb_test/kinet2pcb_test-cache.lib
tests/kinet2pcb_test/kinet2pcb_test.net
tests/kinet2pcb_test/kinet2pcb_test.pro
tests/kinet2pcb_test/kinet2pcb_test.sch