Metadata-Version: 2.1
Name: kinet2pcb
Version: 1.1.1
Summary: Convert KiCad netlist into a PCBNEW .kicad_pcb file.
Home-page: https://github.com/devbisme/kinet2pcb
Author: Dave Vandenbout
Author-email: devb@xess.com
License: MIT license
Project-URL: Documentation, https://devbisme.github.io/kinet2pcb
Project-URL: Source, https://github.com/devbisme/kinet2pcb
Project-URL: Changelog, https://github.com/devbisme/kinet2pcb/blob/master/HISTORY.rst
Project-URL: Tracker, https://github.com/devbisme/kinet2pcb/issues
Keywords: kinet2pcb KiCad EDA PCBNEW SKiDL
Classifier: Development Status :: 5 - Production/Stable
Classifier: Intended Audience :: Manufacturing
Classifier: License :: OSI Approved :: MIT License
Classifier: Natural Language :: English
Classifier: Operating System :: OS Independent
Classifier: Programming Language :: Python :: 2.7
Classifier: Programming Language :: Python :: 3
Classifier: Topic :: Scientific/Engineering :: Electronic Design Automation (EDA)
License-File: LICENSE
License-File: AUTHORS.rst
